KaftaLibrary/__init__.py
KaftaLibrary/keywords.py
KafkaRobotLibrary-0.1.0.dist-info/METADATA
KafkaRobotLibrary-0.1.0.dist-info/WHEEL
KafkaRobotLibrary-0.1.0.dist-info/top_level.txt
KafkaRobotLibrary-0.1.0.dist-info/RECORD
