Metadata-Version: 2.1
Name: KafkaRobotLibrary
Version: 0.1.0
Summary: Uma biblioteca do Robot Framework para interação com o Kafka.
Author: Andre Nunes
Author-email: andre.nunes@gmail.com
Keywords: robotframework kafka testing
Classifier: Programming Language :: Python :: 3
Classifier: License :: OSI Approved :: MIT License
Classifier: Operating System :: OS Independent
Classifier: Framework :: Robot Framework
Requires-Dist: kafka-python
Requires-Dist: robotframework
